{
	"dialogue": [
		{
			"expression": "angry",
			"text": "Come on! I don't have time for this! HE might-",
			"boxState": "angry",
			"portrait": "elexa",
			"speed": 0.05
		},
		{
			"expression": "talk",
			"text": "*CRASH!*",
			"boxState": "angry",
			"speed": 0.05,
			"portrait": "zero"
		},
		{
			"expression": "disgust",
			"text": "Oh, goodness.",
			"boxState": "normal",
			"portrait": "elexa",
			"speed": 0.05
		},
		{
			"expression": "talk",
			"text": "(A tall, white figure emerged from a chamber in front of the two.)",
			"boxState": "normal",
			"portrait": "zero",
			"speed": 0.05
		},
		{
			"expression": "furious",
			"text": "BEEP!",
			"boxState": "angry",
			"speed": 0.05,
			"portrait": "bfzd"
		},
		{
			"expression": "shocked",
			"text": "Wh-What is that thing?!",
			"boxState": "angry",
			"speed": 0.05,
			"portrait": "gfzd"
		},
		{
			"expression": "angry",
			"text": "I don't have time to explain; we need to find a way to sedate it!",
			"boxState": "angry",
			"speed": 0.05,
			"portrait": "elexa"
		},
		{
			"expression": "talk",
			"text": "You, with the blue hair! We need to keep singing!",
			"boxState": "normal",
			"speed": 0.05,
			"portrait": "elexa"
		},
		{
			"expression": "confused",
			"text": "Bee-",
			"boxState": "normal",
			"speed": 0.05,
			"portrait": "bfzd"
		}
	]
}